drf_notifications-1.0.0.dist-info/licenses/AUTHORS.txt
drf_notifications-1.0.0.dist-info/licenses/LICENSE.txt
notifications/__init__.py
notifications/admin.py
notifications/apps.py
notifications/helpers.py
notifications/models.py
notifications/serializers.py
notifications/settings.py
notifications/signals.py
notifications/urls.py
notifications/utils.py
notifications/views.py
notifications/locale/id/LC_MESSAGES/django.po
notifications/locale/ru/LC_MESSAGES/django.po
notifications/migrations/0001_initial.py
notifications/migrations/__init__.py
notifications/templatetags/__init__.py
notifications/templatetags/notifications_tags.py
notifications/tests/__init__.py
notifications/tests/settings.py
notifications/tests/tests.py
notifications/tests/urls.py
notifications/tests/views.py
notifications/tests/sample_notifications/__init__.py
notifications/tests/sample_notifications/admin.py
notifications/tests/sample_notifications/apps.py
notifications/tests/sample_notifications/models.py
notifications/tests/sample_notifications/tests.py
notifications/tests/sample_notifications/migrations/0001_initial.py
notifications/tests/sample_notifications/migrations/__init__.py
notifications/tests/sample_notifications/templatetags/__init__.py
notifications/tests/sample_notifications/templatetags/notifications_tags.py
notifications/tests/templates/test_live.html
notifications/tests/test_models/models.py
notifications/tests/test_models/migrations/0001_initial.py
notifications/tests/test_models/migrations/__init__.py
drf_notifications-1.0.0.dist-info/METADATA
drf_notifications-1.0.0.dist-info/WHEEL
drf_notifications-1.0.0.dist-info/top_level.txt
drf_notifications-1.0.0.dist-info/RECORD
