Metadata-Version: 2.4
Name: drf-notifications
Version: 1.0.0
Summary: GitHub notifications alike app for Django.
Home-page: https://github.com/soomroaaqib/drf-notifications.git
Author: django-notifications team
Author-email: soomroaaqib55@gmail.com
License: BSD
Keywords: django notifications github action event stream drf rest_framework api
Classifier: Development Status :: 5 - Production/Stable
Classifier: Environment :: Web Environment
Classifier: Framework :: Django
Classifier: Intended Audience :: Developers
Classifier: License :: OSI Approved :: BSD License
Classifier: Operating System :: OS Independent
Classifier: Framework :: Django
Classifier: Framework :: Django :: 4.2
Classifier: Framework :: Django :: 5.0
Classifier: Framework :: Django :: 5.1
Classifier: Framework :: Django :: 5.2
Classifier: Programming Language :: Python
Classifier: Programming Language :: Python :: 3
Classifier: Programming Language :: Python :: 3.9
Classifier: Programming Language :: Python :: 3.10
Classifier: Programming Language :: Python :: 3.11
Classifier: Programming Language :: Python :: 3.12
Classifier: Programming Language :: Python :: 3.13
Classifier: Topic :: Utilities
License-File: LICENSE.txt
License-File: AUTHORS.txt
Requires-Dist: django>=4.2
Requires-Dist: django-model-utils>=3.1.0
Requires-Dist: jsonfield>=2.1.0
Requires-Dist: swapper
Requires-Dist: packaging
Requires-Dist: djangorestframework==3.16.0
Dynamic: author
Dynamic: author-email
Dynamic: classifier
Dynamic: description
Dynamic: description-content-type
Dynamic: home-page
Dynamic: keywords
Dynamic: license
Dynamic: license-file
Dynamic: requires-dist
Dynamic: summary
